{
"type": "FeatureCollection",
"name": "TheWildFig_json",
"crs": { "type": "name", "properties": { "name": "urn:ogc:def:crs:OGC:1.3:CRS84" } },
"features": [
{ "type": "Feature", "properties": { "id": null }, "geometry": null },
{ "type": "Feature", "properties": { "id": null }, "geometry": { "type": "Point", "coordinates": [ -106.82021425943536, 39.188993558780801 ] } }
]
}
